rluafunctions/__init__.py
rluafunctions/os/__init__.py
rluafunctions/task/__init__.py
rluafunctions-0.1.1.dist-info/LICENSE
rluafunctions-0.1.1.dist-info/METADATA
rluafunctions-0.1.1.dist-info/WHEEL
rluafunctions-0.1.1.dist-info/top_level.txt
rluafunctions-0.1.1.dist-info/RECORD
