Metadata-Version: 2.1
Name: rluafunctions
Version: 0.1.1
Summary: Use common rlua functions and libraries in Python
Home-page: https://github.com/roninmaster21/rluafunctions
Author: roninmaster21
Author-email: 
License: MIT
Project-URL: Bug Tracker, https://github.com/roninmaster21/rluafunctions/issues
License-File: LICENSE
